<ObjectDefinition>
  <information>
    <icon>none</icon>
    <description></description>
    <displayField>object_id</displayField>
    <order>0</order>
    <visibility/>
    <wfConstraintsPath></wfConstraintsPath>
    <configType>cli</configType>
    <createTemplateId></createTemplateId>
    <createTemplateObject></createTemplateObject>
    <defaultDisplay>false</defaultDisplay>
    <dynamic>false</dynamic>
    <importIfMandatoryPresent>false</importIfMandatoryPresent>
    <maxInstances>0</maxInstances>
    <relatedObjects></relatedObjects>
    <retainIfImportIsEmpty>false</retainIfImportIsEmpty>
    <name>FirewallPolicy</name>
    <group>SASE</group>
    <importonce>false</importonce>
    <importrank>0</importrank>
    <reorderinstances>false</reorderinstances>
    <sortascending>false</sortascending>
    <sortauto>false</sortauto>
    <sortnumerical>false</sortnumerical>
    <sortvariable>params._order</sortvariable>
    <directoryNames>
      <directoryName>SASE</directoryName>
    </directoryNames>
  </information>
  <variables frozen="0">
    <variable displayName="name" name="params.object_id" startIncrement="0" type="String" mandatoryArray="false" visible="true" description="" groupSeparator="" groupDisplayName="" maxLength="100" displayOrder="0" increment="0" refServiceURI="" keepOnImport="false" editable="false" uniqueItemsInDropDownList="false" onlyDetailView="false" createOnlyView="false" localVarNameMatch="" remoteVarNameMatch="" localVarToFilter="" remoteVarToFilter="" remoteVarValueToFilter="" arrayCanAdd="true" arrayCanRemove="true" arrayCanMove="true" arrayCanEdit="true" arrayMinSizeRequired="false" frozen="false" displayNameHeader="" fullDisplayName="" isCompositeKey="false" shared="false" isMandatory="true" isUserLocked="false" isEditLocked="false" isGrouped="false" isSearchable="false" isUniqueGlobal="false"/>
    <variable displayName="action" name="params.action" startIncrement="0" type="String" mandatoryArray="false" visible="true" description="" groupSeparator="" groupDisplayName="" maxLength="100" displayOrder="0" increment="0" refServiceURI="" keepOnImport="false" editable="false" uniqueItemsInDropDownList="false" onlyDetailView="false" createOnlyView="false" localVarNameMatch="" remoteVarNameMatch="" localVarToFilter="" remoteVarToFilter="" remoteVarValueToFilter="" arrayCanAdd="true" arrayCanRemove="true" arrayCanMove="true" arrayCanEdit="true" arrayMinSizeRequired="false" frozen="false" displayNameHeader="" fullDisplayName="" isCompositeKey="false" shared="false" default="permit" isMandatory="true" isUserLocked="false" isEditLocked="false" isGrouped="false" isSearchable="false" isUniqueGlobal="false">
      <values>
        <values displayValue="permit">permit</values>
        <values displayValue="deny">deny</values>
      </values>
    </variable>
    <variable displayName="proto" name="params.proto" startIncrement="0" type="String" mandatoryArray="false" visible="true" description="" groupSeparator="" groupDisplayName="" maxLength="100" displayOrder="0" increment="0" refServiceURI="" keepOnImport="false" editable="false" uniqueItemsInDropDownList="false" onlyDetailView="false" createOnlyView="false" localVarNameMatch="" remoteVarNameMatch="" localVarToFilter="" remoteVarToFilter="" remoteVarValueToFilter="" arrayCanAdd="true" arrayCanRemove="true" arrayCanMove="true" arrayCanEdit="true" arrayMinSizeRequired="false" frozen="false" displayNameHeader="" fullDisplayName="" isCompositeKey="false" shared="false" default="ip" isMandatory="true" isUserLocked="false" isEditLocked="false" isGrouped="false" isSearchable="false" isUniqueGlobal="false">
      <values>
        <values displayValue="ip">ip</values>
      </values>
    </variable>
    <variable displayName="source" name="params.source" startIncrement="0" type="ObjectRef" mandatoryArray="false" visible="true" description="" groupSeparator="" groupDisplayName="" maxLength="100" displayOrder="0" increment="0" refServiceURI="" keepOnImport="false" editable="false" uniqueItemsInDropDownList="false" onlyDetailView="false" createOnlyView="false" localVarNameMatch="" remoteVarNameMatch="" localVarToFilter="" remoteVarToFilter="" remoteVarValueToFilter="" arrayCanAdd="true" arrayCanRemove="true" arrayCanMove="true" arrayCanEdit="true" arrayMinSizeRequired="false" frozen="false" displayNameHeader="" fullDisplayName="" isCompositeKey="false" shared="false" default="any" isMandatory="true" isUserLocked="false" isEditLocked="false" isGrouped="false" isSearchable="false" isUniqueGlobal="false">
      <classes>
        <class>AddressGroup</class>
      </classes>
    </variable>
    <variable displayName="destination" name="params.destination" startIncrement="0" type="ObjectRef" mandatoryArray="false" visible="true" description="" groupSeparator="" groupDisplayName="" maxLength="100" displayOrder="0" increment="0" refServiceURI="" keepOnImport="false" editable="false" uniqueItemsInDropDownList="false" onlyDetailView="false" createOnlyView="false" localVarNameMatch="" remoteVarNameMatch="" localVarToFilter="" remoteVarToFilter="" remoteVarValueToFilter="" arrayCanAdd="true" arrayCanRemove="true" arrayCanMove="true" arrayCanEdit="true" arrayMinSizeRequired="false" frozen="false" displayNameHeader="" fullDisplayName="" isCompositeKey="false" shared="false" isMandatory="false" isUserLocked="false" isEditLocked="false" isGrouped="false" isSearchable="false" isUniqueGlobal="false">
      <classes>
        <class>AddressGroup</class>
      </classes>
    </variable>
    <variable displayName="Version" name="params.version" startIncrement="0" type="String" mandatoryArray="false" visible="false" description="" groupSeparator="" groupDisplayName="" maxLength="100" displayOrder="5" increment="0" refServiceURI="" keepOnImport="false" editable="false" uniqueItemsInDropDownList="false" onlyDetailView="false" createOnlyView="false" localVarNameMatch="" remoteVarNameMatch="" localVarToFilter="" remoteVarToFilter="" remoteVarValueToFilter="" arrayCanAdd="true" arrayCanRemove="true" arrayCanMove="true" arrayCanEdit="true" arrayMinSizeRequired="false" frozen="false" displayNameHeader="" fullDisplayName="" isCompositeKey="false" shared="false" default="ipv4" isMandatory="false" isUserLocked="false" isEditLocked="false" isGrouped="false" isSearchable="false" isUniqueGlobal="false">
      <values>
        <values displayValue="ipv4">ipv4</values>
        <values displayValue="ipv6">ipv6</values>
      </values>
    </variable>
  </variables>
  <example>
    <content>ip access-list extended netskope-web-acl
 10 permit tcp any any eq 443
 20 permit tcp any any eq www
 30 permit icmp any host 123.4.4.4
 40 permit icmp any host 81.1.3.126
 50 permit ip any host 10.174.6.209
ip access-list extended whitelist_ela_rule_policy
 11 permit tcp any host 2.2.2.2 eq 45
 200 permit udp any host 2.2.2.2 eq 45
 300 permit ip any object-group test_group
 50 permit ip any host 10.174.6.209
ip access-list extended test
 10 deny icmp any any
 20 deny tcp any host 2.2.2.2 eq 45
ip access-list extended whitelist_test_group
 10 permit ip any any</content>
  </example>
  <command name="IMPORT">
    <operation><![CDATA[sho run | sec  ip access-list extended]]></operation>
    <parser>
      <section>
        <regexp>@^ip access-list extended whitelist_(?&lt;object_id&gt;\S+)$@</regexp>
      </section>
      <lines>
        <line>
          <regexp></regexp>
          <xpath></xpath>
        </line>
        <line>
          <regexp></regexp>
          <xpath></xpath>
        </line>
        <line>
          <regexp></regexp>
          <xpath></xpath>
        </line>
        <line>
          <regexp></regexp>
          <xpath></xpath>
        </line>
        <line>
          <regexp></regexp>
          <xpath></xpath>
        </line>
        <line>
          <regexp></regexp>
          <xpath></xpath>
        </line>
        <line>
          <regexp></regexp>
          <xpath></xpath>
        </line>
        <line>
          <regexp></regexp>
          <xpath></xpath>
        </line>
        <line>
          <regexp>@^ \d+ (?&lt;action&gt;\S+)\s+(?&lt;proto&gt;\S+) (?&lt;source&gt;any) object-group (?&lt;destination&gt;\S+)$@</regexp>
          <xpath></xpath>
        </line>
        <line>
          <regexp>@^ \d+ (?&lt;action&gt;\S+)\s+(?&lt;proto&gt;\S+) (?&lt;source&gt;any) (?&lt;destination&gt;\S+)$@</regexp>
          <xpath></xpath>
        </line>
        <ignore>
          <regexp>@^ \d+ (?&lt;action&gt;\S+)\s+(?&lt;proto&gt;\S+) (?&lt;source&gt;any) host (?&lt;destination&gt;\S+) eq (?&lt;port&gt;\S+)$@</regexp>
        </ignore>
      </lines>
    </parser>
  </command>
  <command name="CREATE">
    <operation><![CDATA[ip access-list extended whitelist_{$params.object_id}
{$params.action} {$params.proto} {$params.source} object-group {$params.destination}]]></operation>
  </command>
  <command name="READ"/>
  <command name="UPDATE">
    <operation><![CDATA[ip access-list extended whitelist_{$params.object_id}
{$params.action} {$params.proto} {$params.source} object-group {$params.destination}]]></operation>
  </command>
  <command name="CONSTRAINT"/>
  <command name="DELETE">
    <operation><![CDATA[no ip access-list extended whitelist_{$params.object_id}]]></operation>
  </command>
  <command name="LIST"/>
  <displayName>FirewallPolicy</displayName>
  <order>0</order>
</ObjectDefinition>
